[{"skeleton_id": 2439134, "color": "#fdf490", "opacity": 1.0}, {"skeleton_id": 4391317, "color": "#fdf490", "opacity": 1.0}, {"skeleton_id": 5053417, "color": "#fdf490", "opacity": 1.0}, {"skeleton_id": 5874480, "color": "#fdf490", "opacity": 1.0}, {"skeleton_id": 5938794, "color": "#fdf490", "opacity": 1.0}, {"skeleton_id": 5963873, "color": "#fdf490", "opacity": 1.0}, {"skeleton_id": 9078240, "color": "#fdf490", "opacity": 1.0}, {"skeleton_id": 9983417, "color": "#fdf490", "opacity": 1.0}, {"skeleton_id": 11656349, "color": "#fdf490", "opacity": 1.0}, {"skeleton_id": 11703922, "color": "#fdf490", "opacity": 1.0}, {"skeleton_id": 11853038, "color": "#fdf490", "opacity": 1.0}, {"skeleton_id": 12299621, "color": "#fdf490", "opacity": 1.0}, {"skeleton_id": 13206239, "color": "#fdf490", "opacity": 1.0}, {"skeleton_id": 15766806, "color": "#fdf490", "opacity": 1.0}, {"skeleton_id": 16316916, "color": "#fdf490", "opacity": 1.0}, {"skeleton_id": 16442113, "color": "#fdf490", "opacity": 1.0}, {"skeleton_id": 4099900, "color": "#fdf490", "opacity": 1.0}, {"skeleton_id": 11826171, "color": "#fdf490", "opacity": 1.0}, {"skeleton_id": 16188942, "color": "#fdf490", "opacity": 1.0}, {"skeleton_id": 17058350, "color": "#fdf490", "opacity": 1.0}, {"skeleton_id": 8310955, "color": "#fdf490", "opacity": 1.0}, {"skeleton_id": 4101621, "color": "#fdf490", "opacity": 1.0}, {"skeleton_id": 7688300, "color": "#fdf490", "opacity": 1.0}, {"skeleton_id": 17658884, "color": "#fdf490", "opacity": 1.0}, {"skeleton_id": 16297403, "color": "#fdf490", "opacity": 1.0}, {"skeleton_id": 16181377, "color": "#fdf490", "opacity": 1.0}, {"skeleton_id": 12842593, "color": "#fdf490", "opacity": 1.0}, {"skeleton_id": 8034919, "color": "#fdf490", "opacity": 1.0}, {"skeleton_id": 8847957, "color": "#fdf490", "opacity": 1.0}, {"skeleton_id": 13863331, "color": "#fdf490", "opacity": 1.0}, {"skeleton_id": 10944822, "color": "#fdf490", "opacity": 1.0}, {"skeleton_id": 5592307, "color": "#fdf490", "opacity": 1.0}, {"skeleton_id": 3814175, "color": "#fdf490", "opacity": 1.0}]