[{"skeleton_id": 9287906, "color": "#1f968b", "opacity": 1.0}, {"skeleton_id": 9507904, "color": "#1f968b", "opacity": 1.0}, {"skeleton_id": 13038489, "color": "#1f968b", "opacity": 1.0}, {"skeleton_id": 11234536, "color": "#1f968b", "opacity": 1.0}, {"skeleton_id": 4234016, "color": "#1f968b", "opacity": 1.0}, {"skeleton_id": 17176819, "color": "#1f968b", "opacity": 1.0}, {"skeleton_id": 3010486, "color": "#1f968b", "opacity": 1.0}, {"skeleton_id": 2854715, "color": "#1f968b", "opacity": 1.0}, {"skeleton_id": 14753815, "color": "#1f968b", "opacity": 1.0}, {"skeleton_id": 17913199, "color": "#1f968b", "opacity": 1.0}, {"skeleton_id": 4337398, "color": "#1f968b", "opacity": 1.0}, {"skeleton_id": 7431625, "color": "#1f968b", "opacity": 1.0}, {"skeleton_id": 867393, "color": "#1f968b", "opacity": 1.0}, {"skeleton_id": 4152272, "color": "#1f968b", "opacity": 1.0}, {"skeleton_id": 2667061, "color": "#1f968b", "opacity": 1.0}, {"skeleton_id": 17867309, "color": "#1f968b", "opacity": 1.0}, {"skeleton_id": 5480553, "color": "#1f968b", "opacity": 1.0}, {"skeleton_id": 5560620, "color": "#1f968b", "opacity": 1.0}, {"skeleton_id": 5516552, "color": "#1f968b", "opacity": 1.0}, {"skeleton_id": 17166682, "color": "#1f968b", "opacity": 1.0}, {"skeleton_id": 17176882, "color": "#1f968b", "opacity": 1.0}, {"skeleton_id": 5326407, "color": "#1f968b", "opacity": 1.0}, {"skeleton_id": 10617840, "color": "#1f968b", "opacity": 1.0}, {"skeleton_id": 10612630, "color": "#1f968b", "opacity": 1.0}, {"skeleton_id": 9585145, "color": "#1f968b", "opacity": 1.0}, {"skeleton_id": 3707204, "color": "#1f968b", "opacity": 1.0}, {"skeleton_id": 4190567, "color": "#1f968b", "opacity": 1.0}, {"skeleton_id": 9287199, "color": "#1f968b", "opacity": 1.0}, {"skeleton_id": 5476653, "color": "#1f968b", "opacity": 1.0}, {"skeleton_id": 5592307, "color": "#1f968b", "opacity": 1.0}, {"skeleton_id": 15674269, "color": "#1f968b", "opacity": 1.0}, {"skeleton_id": 17850822, "color": "#1f968b", "opacity": 1.0}, {"skeleton_id": 19857573, "color": "#1f968b", "opacity": 1.0}, {"skeleton_id": 4201555, "color": "#1f968b", "opacity": 1.0}, {"skeleton_id": 17278502, "color": "#1f968b", "opacity": 1.0}, {"skeleton_id": 10855798, "color": "#1f968b", "opacity": 1.0}, {"skeleton_id": 15068806, "color": "#1f968b", "opacity": 1.0}, {"skeleton_id": 9841469, "color": "#1f968b", "opacity": 1.0}, {"skeleton_id": 17658884, "color": "#1f968b", "opacity": 1.0}, {"skeleton_id": 6250655, "color": "#1f968b", "opacity": 1.0}, {"skeleton_id": 16188942, "color": "#1f968b", "opacity": 1.0}, {"skeleton_id": 16297403, "color": "#1f968b", "opacity": 1.0}, {"skeleton_id": 5590611, "color": "#1f968b", "opacity": 1.0}, {"skeleton_id": 11637003, "color": "#1f968b", "opacity": 1.0}, {"skeleton_id": 9767705, "color": "#1f968b", "opacity": 1.0}]