[{"skeleton_id": 20443457, "color": "#472d7b", "opacity": 1.0}, {"skeleton_id": 13674287, "color": "#472d7b", "opacity": 1.0}, {"skeleton_id": 9507904, "color": "#472d7b", "opacity": 1.0}, {"skeleton_id": 13806524, "color": "#472d7b", "opacity": 1.0}, {"skeleton_id": 17176819, "color": "#472d7b", "opacity": 1.0}, {"skeleton_id": 17913199, "color": "#472d7b", "opacity": 1.0}, {"skeleton_id": 4346154, "color": "#472d7b", "opacity": 1.0}, {"skeleton_id": 5771934, "color": "#472d7b", "opacity": 1.0}, {"skeleton_id": 16758011, "color": "#472d7b", "opacity": 1.0}, {"skeleton_id": 5326407, "color": "#472d7b", "opacity": 1.0}, {"skeleton_id": 4515496, "color": "#472d7b", "opacity": 1.0}, {"skeleton_id": 4128002, "color": "#472d7b", "opacity": 1.0}, {"skeleton_id": 19857573, "color": "#472d7b", "opacity": 1.0}, {"skeleton_id": 17278502, "color": "#472d7b", "opacity": 1.0}, {"skeleton_id": 10855798, "color": "#472d7b", "opacity": 1.0}, {"skeleton_id": 17658884, "color": "#472d7b", "opacity": 1.0}, {"skeleton_id": 18570360, "color": "#472d7b", "opacity": 1.0}, {"skeleton_id": 3729504, "color": "#472d7b", "opacity": 1.0}, {"skeleton_id": 3793681, "color": "#472d7b", "opacity": 1.0}]