[{"skeleton_id": 3765735, "color": "#c8e020", "opacity": 1.0}, {"skeleton_id": 15606239, "color": "#c8e020", "opacity": 1.0}, {"skeleton_id": 8546775, "color": "#c8e020", "opacity": 1.0}, {"skeleton_id": 19132527, "color": "#c8e020", "opacity": 1.0}, {"skeleton_id": 13210358, "color": "#c8e020", "opacity": 1.0}, {"skeleton_id": 7422595, "color": "#c8e020", "opacity": 1.0}, {"skeleton_id": 17756162, "color": "#c8e020", "opacity": 1.0}, {"skeleton_id": 3765728, "color": "#c8e020", "opacity": 1.0}, {"skeleton_id": 17980792, "color": "#c8e020", "opacity": 1.0}]