[{"skeleton_id": 10167078, "color": "#eae51a", "opacity": 1.0}, {"skeleton_id": 16223688, "color": "#eae51a", "opacity": 1.0}, {"skeleton_id": 9720614, "color": "#eae51a", "opacity": 1.0}, {"skeleton_id": 7555968, "color": "#eae51a", "opacity": 1.0}, {"skeleton_id": 14753815, "color": "#eae51a", "opacity": 1.0}, {"skeleton_id": 17107661, "color": "#eae51a", "opacity": 1.0}, {"skeleton_id": 17326218, "color": "#eae51a", "opacity": 1.0}, {"skeleton_id": 5946241, "color": "#eae51a", "opacity": 1.0}, {"skeleton_id": 17847543, "color": "#eae51a", "opacity": 1.0}, {"skeleton_id": 5369028, "color": "#eae51a", "opacity": 1.0}, {"skeleton_id": 19048289, "color": "#eae51a", "opacity": 1.0}, {"skeleton_id": 4515496, "color": "#eae51a", "opacity": 1.0}, {"skeleton_id": 20479959, "color": "#eae51a", "opacity": 1.0}, {"skeleton_id": 16617920, "color": "#eae51a", "opacity": 1.0}, {"skeleton_id": 18644088, "color": "#eae51a", "opacity": 1.0}, {"skeleton_id": 3149791, "color": "#eae51a", "opacity": 1.0}, {"skeleton_id": 9806510, "color": "#eae51a", "opacity": 1.0}, {"skeleton_id": 12990900, "color": "#eae51a", "opacity": 1.0}, {"skeleton_id": 10945581, "color": "#eae51a", "opacity": 1.0}, {"skeleton_id": 15607335, "color": "#eae51a", "opacity": 1.0}, {"skeleton_id": 6250655, "color": "#eae51a", "opacity": 1.0}]