[{"skeleton_id": 17784367, "color": "#25848e", "opacity": 1.0}, {"skeleton_id": 3913620, "color": "#25848e", "opacity": 1.0}, {"skeleton_id": 14077615, "color": "#25848e", "opacity": 1.0}, {"skeleton_id": 11528017, "color": "#25848e", "opacity": 1.0}, {"skeleton_id": 4411688, "color": "#25848e", "opacity": 1.0}, {"skeleton_id": 4473922, "color": "#25848e", "opacity": 1.0}, {"skeleton_id": 6611894, "color": "#25848e", "opacity": 1.0}, {"skeleton_id": 11356523, "color": "#25848e", "opacity": 1.0}, {"skeleton_id": 5971400, "color": "#25848e", "opacity": 1.0}, {"skeleton_id": 3793760, "color": "#25848e", "opacity": 1.0}, {"skeleton_id": 13953546, "color": "#25848e", "opacity": 1.0}]