[{"skeleton_id": 2557644, "color": "#acaac8", "opacity": 1.0}, {"skeleton_id": 2920061, "color": "#acaac8", "opacity": 1.0}, {"skeleton_id": 2920554, "color": "#acaac8", "opacity": 1.0}, {"skeleton_id": 3232808, "color": "#acaac8", "opacity": 1.0}, {"skeleton_id": 3814635, "color": "#acaac8", "opacity": 1.0}, {"skeleton_id": 3820148, "color": "#acaac8", "opacity": 1.0}, {"skeleton_id": 3844799, "color": "#acaac8", "opacity": 1.0}, {"skeleton_id": 4311586, "color": "#acaac8", "opacity": 1.0}, {"skeleton_id": 4393049, "color": "#acaac8", "opacity": 1.0}, {"skeleton_id": 4515496, "color": "#acaac8", "opacity": 1.0}, {"skeleton_id": 4620453, "color": "#acaac8", "opacity": 1.0}, {"skeleton_id": 4700182, "color": "#acaac8", "opacity": 1.0}, {"skeleton_id": 4876704, "color": "#acaac8", "opacity": 1.0}, {"skeleton_id": 4983938, "color": "#acaac8", "opacity": 1.0}, {"skeleton_id": 6219781, "color": "#acaac8", "opacity": 1.0}, {"skeleton_id": 6220384, "color": "#acaac8", "opacity": 1.0}, {"skeleton_id": 6250655, "color": "#acaac8", "opacity": 1.0}, {"skeleton_id": 7563413, "color": "#acaac8", "opacity": 1.0}, {"skeleton_id": 7692008, "color": "#acaac8", "opacity": 1.0}, {"skeleton_id": 8065380, "color": "#acaac8", "opacity": 1.0}, {"skeleton_id": 8159396, "color": "#acaac8", "opacity": 1.0}, {"skeleton_id": 8227502, "color": "#acaac8", "opacity": 1.0}, {"skeleton_id": 8254894, "color": "#acaac8", "opacity": 1.0}, {"skeleton_id": 8598886, "color": "#acaac8", "opacity": 1.0}, {"skeleton_id": 9291938, "color": "#acaac8", "opacity": 1.0}, {"skeleton_id": 9565674, "color": "#acaac8", "opacity": 1.0}, {"skeleton_id": 9577562, "color": "#acaac8", "opacity": 1.0}, {"skeleton_id": 9792178, "color": "#acaac8", "opacity": 1.0}, {"skeleton_id": 9806510, "color": "#acaac8", "opacity": 1.0}, {"skeleton_id": 9845997, "color": "#acaac8", "opacity": 1.0}, {"skeleton_id": 10013517, "color": "#acaac8", "opacity": 1.0}, {"skeleton_id": 10158972, "color": "#acaac8", "opacity": 1.0}, {"skeleton_id": 10167116, "color": "#acaac8", "opacity": 1.0}, {"skeleton_id": 10681487, "color": "#acaac8", "opacity": 1.0}, {"skeleton_id": 10682411, "color": "#acaac8", "opacity": 1.0}, {"skeleton_id": 10684539, "color": "#acaac8", "opacity": 1.0}, {"skeleton_id": 10827212, "color": "#acaac8", "opacity": 1.0}, {"skeleton_id": 10945581, "color": "#acaac8", "opacity": 1.0}, {"skeleton_id": 11157622, "color": "#acaac8", "opacity": 1.0}, {"skeleton_id": 11184236, "color": "#acaac8", "opacity": 1.0}, {"skeleton_id": 11714576, "color": "#acaac8", "opacity": 1.0}, {"skeleton_id": 12612426, "color": "#acaac8", "opacity": 1.0}, {"skeleton_id": 13173311, "color": "#acaac8", "opacity": 1.0}, {"skeleton_id": 13358515, "color": "#acaac8", "opacity": 1.0}, {"skeleton_id": 13370624, "color": "#acaac8", "opacity": 1.0}, {"skeleton_id": 13580849, "color": "#acaac8", "opacity": 1.0}, {"skeleton_id": 13634759, "color": "#acaac8", "opacity": 1.0}, {"skeleton_id": 13768622, "color": "#acaac8", "opacity": 1.0}, {"skeleton_id": 13795090, "color": "#acaac8", "opacity": 1.0}, {"skeleton_id": 13858824, "color": "#acaac8", "opacity": 1.0}, {"skeleton_id": 14154154, "color": "#acaac8", "opacity": 1.0}, {"skeleton_id": 15334461, "color": "#acaac8", "opacity": 1.0}, {"skeleton_id": 15547235, "color": "#acaac8", "opacity": 1.0}, {"skeleton_id": 15589591, "color": "#acaac8", "opacity": 1.0}, {"skeleton_id": 15680043, "color": "#acaac8", "opacity": 1.0}, {"skeleton_id": 15718981, "color": "#acaac8", "opacity": 1.0}, {"skeleton_id": 15829660, "color": "#acaac8", "opacity": 1.0}, {"skeleton_id": 16158918, "color": "#acaac8", "opacity": 1.0}, {"skeleton_id": 16316981, "color": "#acaac8", "opacity": 1.0}, {"skeleton_id": 16457812, "color": "#acaac8", "opacity": 1.0}, {"skeleton_id": 16463097, "color": "#acaac8", "opacity": 1.0}, {"skeleton_id": 16586265, "color": "#acaac8", "opacity": 1.0}, {"skeleton_id": 16621864, "color": "#acaac8", "opacity": 1.0}, {"skeleton_id": 16841026, "color": "#acaac8", "opacity": 1.0}, {"skeleton_id": 17132009, "color": "#acaac8", "opacity": 1.0}, {"skeleton_id": 17326213, "color": "#acaac8", "opacity": 1.0}, {"skeleton_id": 17355872, "color": "#acaac8", "opacity": 1.0}, {"skeleton_id": 17529547, "color": "#acaac8", "opacity": 1.0}, {"skeleton_id": 17587452, "color": "#acaac8", "opacity": 1.0}, {"skeleton_id": 17654617, "color": "#acaac8", "opacity": 1.0}, {"skeleton_id": 17658907, "color": "#acaac8", "opacity": 1.0}, {"skeleton_id": 17658927, "color": "#acaac8", "opacity": 1.0}, {"skeleton_id": 17658943, "color": "#acaac8", "opacity": 1.0}, {"skeleton_id": 17819985, "color": "#acaac8", "opacity": 1.0}, {"skeleton_id": 17913185, "color": "#acaac8", "opacity": 1.0}, {"skeleton_id": 18264509, "color": "#acaac8", "opacity": 1.0}, {"skeleton_id": 18302665, "color": "#acaac8", "opacity": 1.0}, {"skeleton_id": 18425189, "color": "#acaac8", "opacity": 1.0}, {"skeleton_id": 19276024, "color": "#acaac8", "opacity": 1.0}]