[{"skeleton_id": 992646, "color": "#a57bb8", "opacity": 1.0}, {"skeleton_id": 2652641, "color": "#a57bb8", "opacity": 1.0}, {"skeleton_id": 3486867, "color": "#a57bb8", "opacity": 1.0}, {"skeleton_id": 4991243, "color": "#a57bb8", "opacity": 1.0}, {"skeleton_id": 5744502, "color": "#a57bb8", "opacity": 1.0}, {"skeleton_id": 5767836, "color": "#a57bb8", "opacity": 1.0}, {"skeleton_id": 7694589, "color": "#a57bb8", "opacity": 1.0}, {"skeleton_id": 8154054, "color": "#a57bb8", "opacity": 1.0}, {"skeleton_id": 8216541, "color": "#a57bb8", "opacity": 1.0}, {"skeleton_id": 9842383, "color": "#a57bb8", "opacity": 1.0}, {"skeleton_id": 11229136, "color": "#a57bb8", "opacity": 1.0}, {"skeleton_id": 11286854, "color": "#a57bb8", "opacity": 1.0}, {"skeleton_id": 11717014, "color": "#a57bb8", "opacity": 1.0}, {"skeleton_id": 11717030, "color": "#a57bb8", "opacity": 1.0}, {"skeleton_id": 11756023, "color": "#a57bb8", "opacity": 1.0}, {"skeleton_id": 12366640, "color": "#a57bb8", "opacity": 1.0}, {"skeleton_id": 12923749, "color": "#a57bb8", "opacity": 1.0}, {"skeleton_id": 13830600, "color": "#a57bb8", "opacity": 1.0}, {"skeleton_id": 13833814, "color": "#a57bb8", "opacity": 1.0}, {"skeleton_id": 15586914, "color": "#a57bb8", "opacity": 1.0}, {"skeleton_id": 15586949, "color": "#a57bb8", "opacity": 1.0}, {"skeleton_id": 15608355, "color": "#a57bb8", "opacity": 1.0}, {"skeleton_id": 15669682, "color": "#a57bb8", "opacity": 1.0}, {"skeleton_id": 16014607, "color": "#a57bb8", "opacity": 1.0}, {"skeleton_id": 16424131, "color": "#a57bb8", "opacity": 1.0}, {"skeleton_id": 16485518, "color": "#a57bb8", "opacity": 1.0}, {"skeleton_id": 16490014, "color": "#a57bb8", "opacity": 1.0}, {"skeleton_id": 16588928, "color": "#a57bb8", "opacity": 1.0}, {"skeleton_id": 17223643, "color": "#a57bb8", "opacity": 1.0}, {"skeleton_id": 17359101, "color": "#a57bb8", "opacity": 1.0}, {"skeleton_id": 17360254, "color": "#a57bb8", "opacity": 1.0}, {"skeleton_id": 17360286, "color": "#a57bb8", "opacity": 1.0}, {"skeleton_id": 17414715, "color": "#a57bb8", "opacity": 1.0}, {"skeleton_id": 17423125, "color": "#a57bb8", "opacity": 1.0}, {"skeleton_id": 17729195, "color": "#a57bb8", "opacity": 1.0}, {"skeleton_id": 17729410, "color": "#a57bb8", "opacity": 1.0}, {"skeleton_id": 17729424, "color": "#a57bb8", "opacity": 1.0}, {"skeleton_id": 17732291, "color": "#a57bb8", "opacity": 1.0}, {"skeleton_id": 17732791, "color": "#a57bb8", "opacity": 1.0}, {"skeleton_id": 18656202, "color": "#a57bb8", "opacity": 1.0}, {"skeleton_id": 19054481, "color": "#a57bb8", "opacity": 1.0}, {"skeleton_id": 19470184, "color": "#a57bb8", "opacity": 1.0}, {"skeleton_id": 3608397, "color": "#a57bb8", "opacity": 1.0}, {"skeleton_id": 3639968, "color": "#a57bb8", "opacity": 1.0}, {"skeleton_id": 3797420, "color": "#a57bb8", "opacity": 1.0}, {"skeleton_id": 12273754, "color": "#a57bb8", "opacity": 1.0}, {"skeleton_id": 17464168, "color": "#a57bb8", "opacity": 1.0}, {"skeleton_id": 15599768, "color": "#a57bb8", "opacity": 1.0}, {"skeleton_id": 12882179, "color": "#a57bb8", "opacity": 1.0}, {"skeleton_id": 5478818, "color": "#a57bb8", "opacity": 1.0}, {"skeleton_id": 1805406, "color": "#a57bb8", "opacity": 1.0}, {"skeleton_id": 20443505, "color": "#a57bb8", "opacity": 1.0}, {"skeleton_id": 8271034, "color": "#a57bb8", "opacity": 1.0}, {"skeleton_id": 858479, "color": "#a57bb8", "opacity": 1.0}, {"skeleton_id": 4541081, "color": "#a57bb8", "opacity": 1.0}, {"skeleton_id": 6219445, "color": "#a57bb8", "opacity": 1.0}, {"skeleton_id": 17529547, "color": "#a57bb8", "opacity": 1.0}, {"skeleton_id": 8942413, "color": "#a57bb8", "opacity": 1.0}, {"skeleton_id": 10683313, "color": "#a57bb8", "opacity": 1.0}, {"skeleton_id": 20344845, "color": "#a57bb8", "opacity": 1.0}, {"skeleton_id": 9606496, "color": "#a57bb8", "opacity": 1.0}, {"skeleton_id": 9750356, "color": "#a57bb8", "opacity": 1.0}, {"skeleton_id": 17897298, "color": "#a57bb8", "opacity": 1.0}, {"skeleton_id": 16057212, "color": "#a57bb8", "opacity": 1.0}, {"skeleton_id": 16316981, "color": "#a57bb8", "opacity": 1.0}, {"skeleton_id": 16176721, "color": "#a57bb8", "opacity": 1.0}, {"skeleton_id": 17658672, "color": "#a57bb8", "opacity": 1.0}, {"skeleton_id": 3122533, "color": "#a57bb8", "opacity": 1.0}, {"skeleton_id": 8410627, "color": "#a57bb8", "opacity": 1.0}, {"skeleton_id": 13167025, "color": "#a57bb8", "opacity": 1.0}, {"skeleton_id": 9161929, "color": "#a57bb8", "opacity": 1.0}, {"skeleton_id": 17355892, "color": "#a57bb8", "opacity": 1.0}, {"skeleton_id": 3251140, "color": "#a57bb8", "opacity": 1.0}, {"skeleton_id": 865151, "color": "#a57bb8", "opacity": 1.0}, {"skeleton_id": 4393350, "color": "#a57bb8", "opacity": 1.0}, {"skeleton_id": 17360225, "color": "#a57bb8", "opacity": 1.0}, {"skeleton_id": 8247641, "color": "#a57bb8", "opacity": 1.0}, {"skeleton_id": 5559657, "color": "#a57bb8", "opacity": 1.0}, {"skeleton_id": 16463097, "color": "#a57bb8", "opacity": 1.0}, {"skeleton_id": 5545085, "color": "#a57bb8", "opacity": 1.0}, {"skeleton_id": 1141813, "color": "#a57bb8", "opacity": 1.0}, {"skeleton_id": 8821758, "color": "#a57bb8", "opacity": 1.0}, {"skeleton_id": 17659219, "color": "#a57bb8", "opacity": 1.0}, {"skeleton_id": 15334461, "color": "#a57bb8", "opacity": 1.0}, {"skeleton_id": 12335381, "color": "#a57bb8", "opacity": 1.0}, {"skeleton_id": 3732322, "color": "#a57bb8", "opacity": 1.0}, {"skeleton_id": 3650600, "color": "#a57bb8", "opacity": 1.0}, {"skeleton_id": 18630153, "color": "#a57bb8", "opacity": 1.0}, {"skeleton_id": 5558724, "color": "#a57bb8", "opacity": 1.0}, {"skeleton_id": 10663559, "color": "#a57bb8", "opacity": 1.0}, {"skeleton_id": 17654624, "color": "#a57bb8", "opacity": 1.0}, {"skeleton_id": 8641784, "color": "#a57bb8", "opacity": 1.0}]