[{"skeleton_id": 2979675, "color": "#6ecfa7", "opacity": 1.0}, {"skeleton_id": 3048606, "color": "#6ecfa7", "opacity": 1.0}, {"skeleton_id": 3944330, "color": "#6ecfa7", "opacity": 1.0}, {"skeleton_id": 4110483, "color": "#6ecfa7", "opacity": 1.0}, {"skeleton_id": 4400767, "color": "#6ecfa7", "opacity": 1.0}, {"skeleton_id": 5690425, "color": "#6ecfa7", "opacity": 1.0}, {"skeleton_id": 5691934, "color": "#6ecfa7", "opacity": 1.0}, {"skeleton_id": 5745110, "color": "#6ecfa7", "opacity": 1.0}, {"skeleton_id": 10160250, "color": "#6ecfa7", "opacity": 1.0}, {"skeleton_id": 10609443, "color": "#6ecfa7", "opacity": 1.0}, {"skeleton_id": 10893103, "color": "#6ecfa7", "opacity": 1.0}, {"skeleton_id": 11037238, "color": "#6ecfa7", "opacity": 1.0}, {"skeleton_id": 11079069, "color": "#6ecfa7", "opacity": 1.0}, {"skeleton_id": 11084320, "color": "#6ecfa7", "opacity": 1.0}, {"skeleton_id": 11291653, "color": "#6ecfa7", "opacity": 1.0}, {"skeleton_id": 11934261, "color": "#6ecfa7", "opacity": 1.0}, {"skeleton_id": 12452356, "color": "#6ecfa7", "opacity": 1.0}, {"skeleton_id": 12509506, "color": "#6ecfa7", "opacity": 1.0}, {"skeleton_id": 12612426, "color": "#6ecfa7", "opacity": 1.0}, {"skeleton_id": 12654063, "color": "#6ecfa7", "opacity": 1.0}, {"skeleton_id": 12670738, "color": "#6ecfa7", "opacity": 1.0}, {"skeleton_id": 15590793, "color": "#6ecfa7", "opacity": 1.0}, {"skeleton_id": 15632282, "color": "#6ecfa7", "opacity": 1.0}, {"skeleton_id": 16686371, "color": "#6ecfa7", "opacity": 1.0}, {"skeleton_id": 16799809, "color": "#6ecfa7", "opacity": 1.0}, {"skeleton_id": 17102002, "color": "#6ecfa7", "opacity": 1.0}, {"skeleton_id": 17277623, "color": "#6ecfa7", "opacity": 1.0}, {"skeleton_id": 17321919, "color": "#6ecfa7", "opacity": 1.0}, {"skeleton_id": 17360010, "color": "#6ecfa7", "opacity": 1.0}, {"skeleton_id": 17360022, "color": "#6ecfa7", "opacity": 1.0}, {"skeleton_id": 17473163, "color": "#6ecfa7", "opacity": 1.0}, {"skeleton_id": 17776982, "color": "#6ecfa7", "opacity": 1.0}, {"skeleton_id": 17804729, "color": "#6ecfa7", "opacity": 1.0}, {"skeleton_id": 18087179, "color": "#6ecfa7", "opacity": 1.0}, {"skeleton_id": 18149325, "color": "#6ecfa7", "opacity": 1.0}, {"skeleton_id": 18500915, "color": "#6ecfa7", "opacity": 1.0}, {"skeleton_id": 19880680, "color": "#6ecfa7", "opacity": 1.0}, {"skeleton_id": 17729335, "color": "#6ecfa7", "opacity": 1.0}, {"skeleton_id": 5746180, "color": "#6ecfa7", "opacity": 1.0}, {"skeleton_id": 11029359, "color": "#6ecfa7", "opacity": 1.0}, {"skeleton_id": 17732737, "color": "#6ecfa7", "opacity": 1.0}, {"skeleton_id": 15680043, "color": "#6ecfa7", "opacity": 1.0}, {"skeleton_id": 12371688, "color": "#6ecfa7", "opacity": 1.0}, {"skeleton_id": 11055480, "color": "#6ecfa7", "opacity": 1.0}, {"skeleton_id": 16059134, "color": "#6ecfa7", "opacity": 1.0}, {"skeleton_id": 7422253, "color": "#6ecfa7", "opacity": 1.0}, {"skeleton_id": 3009700, "color": "#6ecfa7", "opacity": 1.0}, {"skeleton_id": 5890323, "color": "#6ecfa7", "opacity": 1.0}, {"skeleton_id": 15732050, "color": "#6ecfa7", "opacity": 1.0}, {"skeleton_id": 17587730, "color": "#6ecfa7", "opacity": 1.0}, {"skeleton_id": 13751194, "color": "#6ecfa7", "opacity": 1.0}, {"skeleton_id": 17326218, "color": "#6ecfa7", "opacity": 1.0}, {"skeleton_id": 19010160, "color": "#6ecfa7", "opacity": 1.0}, {"skeleton_id": 4127926, "color": "#6ecfa7", "opacity": 1.0}, {"skeleton_id": 7429933, "color": "#6ecfa7", "opacity": 1.0}, {"skeleton_id": 3450751, "color": "#6ecfa7", "opacity": 1.0}, {"skeleton_id": 6114695, "color": "#6ecfa7", "opacity": 1.0}, {"skeleton_id": 9720614, "color": "#6ecfa7", "opacity": 1.0}, {"skeleton_id": 7719118, "color": "#6ecfa7", "opacity": 1.0}, {"skeleton_id": 12990900, "color": "#6ecfa7", "opacity": 1.0}, {"skeleton_id": 8412625, "color": "#6ecfa7", "opacity": 1.0}, {"skeleton_id": 6250655, "color": "#6ecfa7", "opacity": 1.0}, {"skeleton_id": 10986253, "color": "#6ecfa7", "opacity": 1.0}, {"skeleton_id": 15679639, "color": "#6ecfa7", "opacity": 1.0}, {"skeleton_id": 17378548, "color": "#6ecfa7", "opacity": 1.0}, {"skeleton_id": 16884085, "color": "#6ecfa7", "opacity": 1.0}, {"skeleton_id": 8840343, "color": "#6ecfa7", "opacity": 1.0}, {"skeleton_id": 11623145, "color": "#6ecfa7", "opacity": 1.0}, {"skeleton_id": 15431795, "color": "#6ecfa7", "opacity": 1.0}, {"skeleton_id": 16369928, "color": "#6ecfa7", "opacity": 1.0}, {"skeleton_id": 1065967, "color": "#6ecfa7", "opacity": 1.0}, {"skeleton_id": 10013517, "color": "#6ecfa7", "opacity": 1.0}, {"skeleton_id": 4215611, "color": "#6ecfa7", "opacity": 1.0}, {"skeleton_id": 14755393, "color": "#6ecfa7", "opacity": 1.0}, {"skeleton_id": 16571210, "color": "#6ecfa7", "opacity": 1.0}, {"skeleton_id": 11081239, "color": "#6ecfa7", "opacity": 1.0}, {"skeleton_id": 17378648, "color": "#6ecfa7", "opacity": 1.0}, {"skeleton_id": 14757050, "color": "#6ecfa7", "opacity": 1.0}, {"skeleton_id": 17587726, "color": "#6ecfa7", "opacity": 1.0}, {"skeleton_id": 16846902, "color": "#6ecfa7", "opacity": 1.0}, {"skeleton_id": 19508873, "color": "#6ecfa7", "opacity": 1.0}, {"skeleton_id": 8592501, "color": "#6ecfa7", "opacity": 1.0}, {"skeleton_id": 13652117, "color": "#6ecfa7", "opacity": 1.0}, {"skeleton_id": 2663649, "color": "#6ecfa7", "opacity": 1.0}, {"skeleton_id": 18248435, "color": "#6ecfa7", "opacity": 1.0}, {"skeleton_id": 10725068, "color": "#6ecfa7", "opacity": 1.0}, {"skeleton_id": 20443571, "color": "#6ecfa7", "opacity": 1.0}, {"skeleton_id": 8135412, "color": "#6ecfa7", "opacity": 1.0}]